<?xml version='1.0' encoding='UTF-8'?><magicdraw><mergenode id="_2022x_2_131803cf_1705931590242_195770_18775" refElementId="_2022x_2_131803cf_1705931590242_195770_18775" humanType="Merge Node" classType="MergeNode" requireSort="node" icon="index_files/icon_mergenode_1976007389.jpg"><visibility humanName="Visibility">public</visibility><qualifiedName humanName="Qualified Name" mode="e">1 - System Description::2 - Control Structure::Oil &amp; Gas Pipeline Context::Operate Pipeline::</qualifiedName><owner refid="_2022x_2_131803cf_1705931482665_143721_18719" refElementId="_2022x_2_131803cf_1705931482665_143721_18719" humanType="Activity" classType="Activity" name="Operate Pipeline" hasDiagram="true" icon="index_files/icon_activity_1388255629.jpg" humanName="Owner" mode="s,e"/><outgoing humanName="Outgoing"><controlflow refid="_2022x_2_131803cf_1705931653970_164986_18789" refElementId="_2022x_2_131803cf_1705931653970_164986_18789" humanType="Control Flow" classType="ControlFlow" name="Control Flow[1 - System Description::2 - Control Structure::Oil &amp; Gas Pipeline Context::Operate Pipeline:: -> 1 - System Description::2 - Control Structure::Oil &amp; Gas Pipeline Context::Operate Pipeline:::Process Order]" isRelationship="true" icon="index_files/icon_controlflow_241456640.jpg"/></outgoing><name humanName="Name" mode="s,e"></name><isLeaf humanName="Is Leaf">false</isLeaf><incoming humanName="Incoming"><controlflow refid="_2022x_2_131803cf_1705931650697_721766_18784" refElementId="_2022x_2_131803cf_1705931650697_721766_18784" humanType="Control Flow" classType="ControlFlow" name="Control Flow[1 - System Description::2 - Control Structure::Oil &amp; Gas Pipeline Context::Operate Pipeline:: -> 1 - System Description::2 - Control Structure::Oil &amp; Gas Pipeline Context::Operate Pipeline::]" isRelationship="true" icon="index_files/icon_controlflow_241456640.jpg"/><controlflow refid="_2022x_2_131803cf_1705932775446_196736_18858" refElementId="_2022x_2_131803cf_1705932775446_196736_18858" humanType="Control Flow" classType="ControlFlow" name="Control Flow[1 - System Description::2 - Control Structure::Oil &amp; Gas Pipeline Context::Operate Pipeline:::Process Order -> 1 - System Description::2 - Control Structure::Oil &amp; Gas Pipeline Context::Operate Pipeline::]" isRelationship="true" icon="index_files/icon_controlflow_241456640.jpg"/></incoming><documentation humanName="Documentation"></documentation><activity refid="_2022x_2_131803cf_1705931482665_143721_18719" refElementId="_2022x_2_131803cf_1705931482665_143721_18719" humanType="Activity" classType="Activity" name="Operate Pipeline" hasDiagram="true" icon="index_files/icon_activity_1388255629.jpg" humanName="Activity"/><TO_DO humanName="To Do" mode="s,e"></TO_DO><ActiveHyperlink humanName="Active Hyperlink"></ActiveHyperlink><report_appliedStereotype_tags humanName="Applied Stereotype" requireSort="element" mode="s,e"/></mergenode></magicdraw>